{
    "collection": {
        "exercise_sid": "c118471e-f243-484b-ba16-9f78a244c465",
        "instrument_id": "0006",
        "period": "2001"
    },
    "data": {
        "10": "30",
        "146": "This is a comment"
    },
    "flushed": false,
    "metadata": {
        "ref_period_end_date": "2019-01-30",
        "ref_period_start_date": "2020-01-01",
        "ru_ref": "49800108249D",
        "user_id": "UNKNOWN"
    },
    "origin": "uk.gov.ons.edc.eq",
    "started_at": "2020-01-05T10:54:11.548611+00:00",
    "submitted_at": "2020-01-05T14:49:33.448608+00:00",
    "type": "uk.gov.ons.edc.eq:surveyresponse",
    "version": "0.0.1",
    "survey_id": "182",
    "case_id": "4d32d367-d725-49ba-8776-a14f5ae035ee"
}