{
  "case_id": "d9e9ce29-d755-4370-b96c-6c4176b722d1",
  "collection": {
    "exercise_sid": "c2be6e5c-551f-4510-989f-2c981b3ffcb4",
    "instrument_id": "0001",
    "period": "201605"
  },
  "data": [
    {
      "answer_id": "answer3746",
      "answer_instance": 0,
      "group_instance": 0,
      "group_instance_id": null,
      "value": "Yes, I am able to report for this period"
    },
    {
      "answer_id": "retail-sales-answer",
      "answer_instance": 0,
      "group_instance": 0,
      "group_instance_id": null,
      "value": 342
    },
    {
      "answer_id": "confirm-zero-retail-sales-answer",
      "answer_instance": 0,
      "group_instance": 0,
      "group_instance_id": null,
      "value": "Yes"
    },
    {
      "answer_id": "online-sales-answer",
      "answer_instance": 0,
      "group_instance": 0,
      "group_instance_id": null,
      "value": 43
    },
    {
      "answer_id": "confirm-online-sales-answer",
      "answer_instance": 0,
      "group_instance": 0,
      "group_instance_id": null,
      "value": "Yes"
    },
    {
      "answer_id": "answer3817",
      "answer_instance": 0,
      "group_instance": 0,
      "group_instance_id": null,
      "value": "Yes"
    },
    {
      "answer_id": "answer3818",
      "answer_instance": 0,
      "group_instance": 0,
      "group_instance_id": null,
      "value": [
        "Weather"
      ]
    },
    {
      "answer_id": "answer3819",
      "answer_instance": 0,
      "group_instance": 0,
      "group_instance_id": null,
      "value": "It Rained"
    },
    {
      "answer_id": "answer3820",
      "answer_instance": 0,
      "group_instance": 0,
      "group_instance_id": null,
      "value": "Yes, there was turnover from other activities"
    },
    {
      "answer_id": "answer3821",
      "answer_instance": 0,
      "group_instance": 0,
      "group_instance_id": null,
      "value": 20
    }
  ],
  "flushed": false,
  "metadata": {
    "ref_period_end_date": "2016-05-31",
    "ref_period_start_date": "2016-05-01",
    "ru_ref": "83682141352S",
    "user_id": "UNKNOWN"
  },
  "origin": "uk.gov.ons.edc.eq",
  "started_at": "2018-11-02T14:31:01.610415",
  "submitted_at": "2018-11-02T14:31:42.062304",
  "survey_id": "281",
  "tx_id": "f368ac5c-da91-4c22-be35-e7bcabba4f53",
  "type": "uk.gov.ons.edc.eq:surveyresponse",
  "version": "0.0.2"
}