{
  "type": "uk.gov.ons.edc.eq:surveyresponse",
  "version": "0.0.1",
  "origin": "uk.gov.ons.edc.eq",
  "survey_id": "139",
  "case_id": "4c0bc9ec-06d4-4f66-88b6-2e42b79f17b3",
  "started_at": "2019-03-23T14:00:24.224709",
  "submitted_at": "2019-03-23T14:50:26.933601",
  "collection": {
    "exercise_sid": "hfjdskf",
    "instrument_id": "0001",
    "period": "1604"
  },
  "metadata": {
    "user_id": "789473423",
    "ru_ref": "12345678901A"
  },
  "data": {
    "51": "84",
    "52": "10",
    "53": "73",
    "54": "24",
    "50": "205",
    "146": "This is a comment field"
  }
}
